animius/Commands.py
animius/Console.py
animius/Model.py
animius/ModelConfig.py
animius/ModelData.py
animius/ParseSubtitle.py
animius/SocketServer.py
animius/SocketServerModel.py
animius/Utils.py
animius/Waifu.py
animius/WordEmbedding.py
animius/__init__.py
animius/Chatbot/ChatbotModel.py
animius/Chatbot/CombinedChatbotModel.py
animius/Chatbot/CombinedPredictionModel.py
animius/Chatbot/ParseData.py
animius/Chatbot/__init__.py
animius/IntentNER/IntentNERModel.py
animius/IntentNER/ParseData.py
animius/IntentNER/__init__.py
animius/SpeakerVerification/MFCC.py
animius/SpeakerVerification/SpeakerVerificationModel.py
animius/SpeakerVerification/__init__.py
animius-1.0.0a1.dist-info/METADATA
animius-1.0.0a1.dist-info/RECORD
animius-1.0.0a1.dist-info/WHEEL
animius-1.0.0a1.dist-info/top_level.txt
