Metadata-Version: 2.1
Name: animius
Version: 1.0.0a1
Summary: A deep-learning virtual assistant engine
Home-page: https://animius.org
Author: gundamMC
Author-email: gundamMC@gundamMC.com
License: Apache 2.0
Keywords: animius ai virtual assistant deep learning
Platform: UNKNOWN
Classifier: Intended Audience :: Developers
Classifier: Programming Language :: Python :: 3
Classifier: License :: OSI Approved :: Apache Software License
Classifier: Topic :: Scientific/Engineering
Classifier: Topic :: Scientific/Engineering :: Mathematics
Classifier: Topic :: Scientific/Engineering :: Artificial Intelligence
Classifier: Topic :: Software Development
Classifier: Topic :: Software Development :: Libraries
Classifier: Topic :: Software Development :: Libraries :: Python Modules
Requires-Python: >=3
Provides-Extra: tf_gpu
Provides-Extra: tf
Requires-Dist: numpy
Requires-Dist: pysubs2
Requires-Dist: pydub
Requires-Dist: scipy
Requires-Dist: speechpy
Provides-Extra: tf
Requires-Dist: tensorflow (==1.12.0); extra == 'tf'
Provides-Extra: tf_gpu
Requires-Dist: tensorflow-gpu (==1.12.0); extra == 'tf_gpu'
